trackman/__init__.py
trackman/admin.py
trackman/api.py
trackman/db_routers.py
trackman/models.py
trackman/settings.py
trackman/signals.py
trackman/tracking.py
trackman/utils.py
trackman/__pycache__/__init__.cpython-310.pyc
trackman/__pycache__/__init__.cpython-311.pyc
trackman/__pycache__/models.cpython-310.pyc
trackman/__pycache__/settings.cpython-310.pyc
trackman/__pycache__/tracking.cpython-310.pyc
trackman/__pycache__/utils.cpython-310.pyc
django_trackman-0.1.1.dist-info/AUTHORS
django_trackman-0.1.1.dist-info/METADATA
django_trackman-0.1.1.dist-info/WHEEL
django_trackman-0.1.1.dist-info/top_level.txt
django_trackman-0.1.1.dist-info/RECORD
