Metadata-Version: 2.1
Name: django-trackman
Version: 0.1.1
Summary: Django Trackman helps with tracking and logging.
Home-page: https://github.com/lazybird/django-trackman/
Author: 
Author-email: 
Keywords: trackman django log logging tracking activity
License-File: AUTHORS
